ncrystal_plugin_WaterData/__init__.py
ncrystal_plugin_WaterData/data/LiquidHeavyWaterD2O_T283.6K.ncmat
ncrystal_plugin_WaterData/data/LiquidHeavyWaterD2O_T293.6K.ncmat
ncrystal_plugin_WaterData/data/LiquidHeavyWaterD2O_T300.0K.ncmat
ncrystal_plugin_WaterData/data/LiquidHeavyWaterD2O_T323.6K.ncmat
ncrystal_plugin_WaterData/data/LiquidHeavyWaterD2O_T350.0K.ncmat
ncrystal_plugin_WaterData/data/LiquidHeavyWaterD2O_T373.6K.ncmat
ncrystal_plugin_WaterData/data/LiquidHeavyWaterD2O_T400.0K.ncmat
ncrystal_plugin_WaterData/data/LiquidHeavyWaterD2O_T423.6K.ncmat
ncrystal_plugin_WaterData/data/LiquidHeavyWaterD2O_T450.0K.ncmat
ncrystal_plugin_WaterData/data/LiquidHeavyWaterD2O_T473.6K.ncmat
ncrystal_plugin_WaterData/data/LiquidHeavyWaterD2O_T500.0K.ncmat
ncrystal_plugin_WaterData/data/LiquidHeavyWaterD2O_T523.6K.ncmat
ncrystal_plugin_WaterData/data/LiquidHeavyWaterD2O_T550.0K.ncmat
ncrystal_plugin_WaterData/data/LiquidHeavyWaterD2O_T573.6K.ncmat
ncrystal_plugin_WaterData/data/LiquidHeavyWaterD2O_T600.0K.ncmat
ncrystal_plugin_WaterData/data/LiquidHeavyWaterD2O_T623.6K.ncmat
ncrystal_plugin_WaterData/data/LiquidWaterH2O_T283.6K.ncmat
ncrystal_plugin_WaterData/data/LiquidWaterH2O_T293.6K.ncmat
ncrystal_plugin_WaterData/data/LiquidWaterH2O_T300.0K.ncmat
ncrystal_plugin_WaterData/data/LiquidWaterH2O_T323.6K.ncmat
ncrystal_plugin_WaterData/data/LiquidWaterH2O_T350.0K.ncmat
ncrystal_plugin_WaterData/data/LiquidWaterH2O_T373.6K.ncmat
ncrystal_plugin_WaterData/data/LiquidWaterH2O_T400.0K.ncmat
ncrystal_plugin_WaterData/data/LiquidWaterH2O_T423.6K.ncmat
ncrystal_plugin_WaterData/data/LiquidWaterH2O_T450.0K.ncmat
ncrystal_plugin_WaterData/data/LiquidWaterH2O_T473.6K.ncmat
ncrystal_plugin_WaterData/data/LiquidWaterH2O_T500.0K.ncmat
ncrystal_plugin_WaterData/data/LiquidWaterH2O_T523.6K.ncmat
ncrystal_plugin_WaterData/data/LiquidWaterH2O_T550.0K.ncmat
ncrystal_plugin_WaterData/data/LiquidWaterH2O_T573.6K.ncmat
ncrystal_plugin_WaterData/data/LiquidWaterH2O_T600.0K.ncmat
ncrystal_plugin_WaterData-0.0.4.dist-info/LICENSE
ncrystal_plugin_WaterData-0.0.4.dist-info/METADATA
ncrystal_plugin_WaterData-0.0.4.dist-info/WHEEL
ncrystal_plugin_WaterData-0.0.4.dist-info/top_level.txt
ncrystal_plugin_WaterData-0.0.4.dist-info/RECORD
