Metadata-Version: 2.2
Name: ncrystal-plugin-WaterData
Version: 0.0.4
Summary: Extra NCMAT data files for light and heavy water.
License: The Apache 2.0 license is reproduced in the following. See the NOTICE file for
Classifier: Programming Language :: Python :: 3
Classifier: License :: OSI Approved :: Apache Software License
License-File: LICENSE
Requires-Dist: ncrystal-pypluginmgr>=0.0.5
